eventsrouter/__init__.py
eventsrouter/admin.py
eventsrouter/apps.py
eventsrouter/authentication.py
eventsrouter/celery.py
eventsrouter/conf.py
eventsrouter/exceptions.py
eventsrouter/signals.py
eventsrouter/urls.py
eventsrouter/fixtures/initial_data.json
eventsrouter/management/__init__.py
eventsrouter/management/commands/__init__.py
eventsrouter/migrations/0001_initial.py
eventsrouter/migrations/0002_event_route.py
eventsrouter/migrations/0003_load_intial_data.py
eventsrouter/migrations/0004_auto_20190228_1930.py
eventsrouter/migrations/0005_auto_20190411_1115.py
eventsrouter/migrations/0005_auto_20190523_1557.py
eventsrouter/migrations/0006_merge_20190523_1236.py
eventsrouter/migrations/__init__.py
eventsrouter/models/Channel.py
eventsrouter/models/Event.py
eventsrouter/models/Route.py
eventsrouter/models/__init__.py
eventsrouter/serializers/__init__.py
eventsrouter/serializers/channel.py
eventsrouter/serializers/route.py
eventsrouter/tasks/__init__.py
eventsrouter/tasks/aws.py
eventsrouter/tasks/webhook.py
eventsrouter/utils/__init__.py
eventsrouter/utils/api_auth.py
eventsrouter/utils/auth.py
eventsrouter/utils/aws.py
eventsrouter/utils/importers.py
eventsrouter/views/__init__.py
eventsrouter/views/events.py
eventsrouter/viewsets/__init__.py
eventsrouter/viewsets/channel.py
eventsrouter/viewsets/route.py
django_slack_events_router-0.0.10.dist-info/LICENSE
django_slack_events_router-0.0.10.dist-info/METADATA
django_slack_events_router-0.0.10.dist-info/WHEEL
django_slack_events_router-0.0.10.dist-info/top_level.txt
django_slack_events_router-0.0.10.dist-info/RECORD
