Metadata-Version: 2.1
Name: django-slack-events-router
Version: 0.0.10
Summary: Routes Slack Events API payloads to their final destination
Home-page: https://github.com/The-Politico/django-slack-events-router
Author: POLITICO interactive news
Author-email: interactives@politico.com
License: MIT
Platform: UNKNOWN
Classifier: Development Status :: 3 - Alpha
Classifier: Framework :: Django
Classifier: Framework :: Django :: 2.0
Classifier: Intended Audience :: Developers
Classifier: Intended Audience :: Information Technology
Classifier: License :: OSI Approved :: MIT License
Classifier: Operating System :: OS Independent
Classifier: Programming Language :: Python :: 3
Classifier: Programming Language :: Python :: 3.5
Classifier: Programming Language :: Python :: 3.6
Classifier: Topic :: Internet :: WWW/HTTP
Requires-Dist: djangorestframework
Requires-Dist: politico-toolbox
Provides-Extra: test
Requires-Dist: pytest ; extra == 'test'
